banking/__init__.py
banking/db/__init__.py
banking/db/create_db.py
banking/db/models.py
banking/logic/__init__.py
banking/logic/rules_bank.py
banking/tests/__init__.py
banking/tests/add_checking_acct.py
banking/tests/add_cust.py
banking/tests/add_savings_acct.py
banking/tests/deposit_to_checking.py
banking/tests/transfer_funds.py
fab_quick_start_util/__init__.py
fab_quick_start_util/fab_quick_start.py
nw/__init__.py
nw/db/__init__.py
nw/db/models.py
nw/logic/__init__.py
nw/logic/model_test.py
nw/logic/rules_bank.py
nw/logic/legacy/__init__.py
nw/logic/legacy/customer_code.py
nw/logic/legacy/order_code.py
nw/logic/legacy/order_detail_code.py
nw/tests/__init__.py
nw/tests/add_cust.py
nw/tests/add_order.py
nw/tests/dlt_order.py
nw/tests/upd_order_customer.py
nw/tests/upd_order_required.py
nw/tests/upd_order_reuse.py
nw/tests/upd_order_shipped.py
nw/tests/upd_order_shipped_auto_commit.py
fab_quick_start-1.0.0.dist-info/LICENSE
fab_quick_start-1.0.0.dist-info/METADATA
fab_quick_start-1.0.0.dist-info/WHEEL
fab_quick_start-1.0.0.dist-info/entry_points.txt
fab_quick_start-1.0.0.dist-info/top_level.txt
fab_quick_start-1.0.0.dist-info/RECORD
