Metadata-Version: 2.1
Name: fab-quick-start
Version: 1.0.0
Summary: Creates FAB view from model, for an instant multi-page, multi-table app.Apps are multi-page: 1 page per table, with page-page navigation for related data.Pages are multi-table: includes related_views, predictive joins.
Home-page: https://github.com/valhuber/fab-quick-start
Author: Val Huber
Author-email: valjhuber@gmail.com
License: BSD
Project-URL: FAB Quick Start Guide, https://github.com/valhuber/fab-quick-start/wiki
Platform: any
Classifier: Development Status :: 3 - Alpha
Classifier: Environment :: Web Environment
Classifier: Intended Audience :: Developers
Classifier: License :: OSI Approved :: BSD License
Classifier: Operating System :: OS Independent
Classifier: Programming Language :: Python
Classifier: Programming Language :: Python :: 3.6
Classifier: Programming Language :: Python :: 3.7
Classifier: Programming Language :: Python :: 3.8
Classifier: Topic :: Software Development :: Libraries :: Python Modules
Requires-Python: ~=3.6
Requires-Dist: apispec[yaml] (<4,>=3.3)
Requires-Dist: colorama (<1,>=0.3.9)
Requires-Dist: click (<8,>=6.7)
Requires-Dist: email-validator (<2,>=1.0.5)
Requires-Dist: Flask (<2,>=0.12)
Requires-Dist: Flask-Babel (<2,>=1)
Requires-Dist: Flask-Login (<0.5,>=0.3)
Requires-Dist: Flask-OpenID (<2,>=1.2.5)
Requires-Dist: Flask-SQLAlchemy (<3,>=2.4)
Requires-Dist: Flask-WTF (<1,>=0.14.2)
Requires-Dist: Flask-JWT-Extended (<4,>=3.18)
Requires-Dist: jsonschema (<4,>=3.0.1)
Requires-Dist: marshmallow (<4,>=3)
Requires-Dist: marshmallow-enum (<2,>=1.5.1)
Requires-Dist: marshmallow-sqlalchemy (<1,>=0.22.0)
Requires-Dist: python-dateutil (<3,>=2.3)
Requires-Dist: prison (<1.0.0,>=0.1.3)
Requires-Dist: PyJWT (>=1.7.1)
Requires-Dist: sqlalchemy-utils (<1,>=0.32.21)
Provides-Extra: jmespath
Requires-Dist: jmespath (>=0.9.5) ; extra == 'jmespath'
